ldm/__init__.py
ldm/lr_scheduler.py
ldm/setup.py
ldm/util.py
ldm/data/__init__.py
ldm/data/base.py
ldm/data/imagenet.py
ldm/data/lsun.py
ldm/models/__init__.py
ldm/models/autoencoder.py
ldm/models/diffusion/__init__.py
ldm/models/diffusion/classifier.py
ldm/models/diffusion/ddim.py
ldm/models/diffusion/ddpm.py
ldm/models/diffusion/plms.py
ldm/modules/__init__.py
ldm/modules/attention.py
ldm/modules/ema.py
ldm/modules/x_transformer.py
ldm/modules/diffusionmodules/__init__.py
ldm/modules/diffusionmodules/model.py
ldm/modules/diffusionmodules/openaimodel.py
ldm/modules/diffusionmodules/util.py
ldm/modules/distributions/__init__.py
ldm/modules/distributions/distributions.py
ldm/modules/encoders/__init__.py
ldm/modules/encoders/modules.py
ldm/modules/image_degradation/__init__.py
ldm/modules/image_degradation/bsrgan.py
ldm/modules/image_degradation/bsrgan_light.py
ldm/modules/image_degradation/utils_image.py
ldm/modules/image_degradation/utils/__init__.py
ldm/modules/losses/__init__.py
ldm/modules/losses/contperceptual.py
ldm/modules/losses/vqperceptual.py
ldm_fix-1.0.1.dist-info/LICENSE
ldm_fix-1.0.1.dist-info/METADATA
ldm_fix-1.0.1.dist-info/WHEEL
ldm_fix-1.0.1.dist-info/top_level.txt
ldm_fix-1.0.1.dist-info/RECORD
