Metadata-Version: 2.1
Name: ldm-fix
Version: 1.0.1
Summary: LDM not exist fix
Home-page: https://github.com/pypa/sampleproject
Author: Anton Marchevskii
Author-email: avatarnarod@gmail.com
Project-URL: Bug Tracker, https://github.com/pypa/sampleproject/issues
Classifier: Programming Language :: Python :: 3
Classifier: License :: OSI Approved :: MIT License
Classifier: Operating System :: OS Independent
Requires-Python: >=3.6
License-File: LICENSE
